photologue/__init__.py
photologue/admin.py
photologue/apps.py
photologue/forms.py
photologue/managers.py
photologue/models.py
photologue/sitemaps.py
photologue/urls.py
photologue/views.py
photologue/locale/ca/LC_MESSAGES/django.mo
photologue/locale/ca/LC_MESSAGES/django.po
photologue/locale/cs/LC_MESSAGES/django.mo
photologue/locale/cs/LC_MESSAGES/django.po
photologue/locale/da/LC_MESSAGES/django.mo
photologue/locale/da/LC_MESSAGES/django.po
photologue/locale/de/LC_MESSAGES/django.mo
photologue/locale/de/LC_MESSAGES/django.po
photologue/locale/en/LC_MESSAGES/django.mo
photologue/locale/en/LC_MESSAGES/django.po
photologue/locale/en_US/LC_MESSAGES/django.mo
photologue/locale/en_US/LC_MESSAGES/django.po
photologue/locale/es_ES/LC_MESSAGES/django.mo
photologue/locale/es_ES/LC_MESSAGES/django.po
photologue/locale/eu/LC_MESSAGES/django.mo
photologue/locale/eu/LC_MESSAGES/django.po
photologue/locale/fr/LC_MESSAGES/django.mo
photologue/locale/fr/LC_MESSAGES/django.po
photologue/locale/hu/LC_MESSAGES/django.mo
photologue/locale/hu/LC_MESSAGES/django.po
photologue/locale/it/LC_MESSAGES/django.mo
photologue/locale/it/LC_MESSAGES/django.po
photologue/locale/nl/LC_MESSAGES/django.mo
photologue/locale/nl/LC_MESSAGES/django.po
photologue/locale/no/LC_MESSAGES/django.mo
photologue/locale/no/LC_MESSAGES/django.po
photologue/locale/pl/LC_MESSAGES/django.mo
photologue/locale/pl/LC_MESSAGES/django.po
photologue/locale/pt/LC_MESSAGES/django.mo
photologue/locale/pt/LC_MESSAGES/django.po
photologue/locale/pt_BR/LC_MESSAGES/django.mo
photologue/locale/pt_BR/LC_MESSAGES/django.po
photologue/locale/ru/LC_MESSAGES/django.mo
photologue/locale/ru/LC_MESSAGES/django.po
photologue/locale/sk/LC_MESSAGES/django.mo
photologue/locale/sk/LC_MESSAGES/django.po
photologue/locale/tr/LC_MESSAGES/django.mo
photologue/locale/tr/LC_MESSAGES/django.po
photologue/locale/tr_TR/LC_MESSAGES/django.mo
photologue/locale/tr_TR/LC_MESSAGES/django.po
photologue/locale/uk/LC_MESSAGES/django.mo
django_photologue-3.18.dist-info/LICENSE.txt
django_photologue-3.18.dist-info/METADATA
django_photologue-3.18.dist-info/WHEEL
django_photologue-3.18.dist-info/top_level.txt
django_photologue-3.18.dist-info/RECORD
