Metadata-Version: 2.1
Name: django-photologue
Version: 3.18
Summary: Powerful image management for the Django web framework.
Home-page: https://github.com/richardbarran/django-photologue
Author: Justin Driscoll, Marcos Daniel Petry, Richard Barran
Author-email: justin@driscolldev.com, marcospetry@gmail.com, richard@arbee-design.co.uk
Classifier: Development Status :: 5 - Production/Stable
Classifier: Environment :: Web Environment
Classifier: Framework :: Django
Classifier: Intended Audience :: Developers
Classifier: License :: OSI Approved :: BSD License
Classifier: Operating System :: OS Independent
Classifier: Programming Language :: Python
Classifier: Programming Language :: Python :: 2.7
Classifier: Programming Language :: Python :: 3
Classifier: Programming Language :: Python :: 3.4
Classifier: Programming Language :: Python :: 3.5
Classifier: Programming Language :: Python :: 3.6
Classifier: Topic :: Utilities
License-File: LICENSE.txt
Requires-Dist: ExifRead (>=3)
Requires-Dist: Pillow (>=10)
Requires-Dist: django-sortedm2m (>=4.0.0)
